c8ydm/__init__.py
c8ydm/main.py
c8ydm/agentmodules/__init__.py
c8ydm/agentmodules/agent_initializer.py
c8ydm/agentmodules/command_handler.py
c8ydm/agentmodules/configfile_download_handler.py
c8ydm/agentmodules/configfile_upload_handler.py
c8ydm/agentmodules/device_profile_listener.py
c8ydm/agentmodules/device_status.py
c8ydm/agentmodules/docker_watcher.py
c8ydm/agentmodules/event_initializer.py
c8ydm/agentmodules/firmware_management.py
c8ydm/agentmodules/logfile_handler.py
c8ydm/agentmodules/measurement_request.py
c8ydm/agentmodules/network.py
c8ydm/agentmodules/remote_access_listener.py
c8ydm/agentmodules/restart.py
c8ydm/agentmodules/sensehat.py
c8ydm/agentmodules/smartRest_inizializer.py
c8ydm/agentmodules/software_management.py
c8ydm/client/__init__.py
c8ydm/client/bootstrap_client.py
c8ydm/client/mqtt_agent.py
c8ydm/client/rest_client.py
c8ydm/core/__init__.py
c8ydm/core/apt_package_manager.py
c8ydm/core/configuration.py
c8ydm/core/device_stats.py
c8ydm/core/docker_watcher.py
c8ydm/core/firmware_manager.py
c8ydm/core/shell.py
c8ydm/framework/__init__.py
c8ydm/framework/modulebase.py
c8ydm/framework/smartrest.py
c8ydm/utils/__init__.py
c8ydm/utils/configutils.py
c8ydm/utils/moduleloader.py
c8ydm/utils/systemutils.py
c8ydm-1.3.7.dist-info/LICENSE
c8ydm-1.3.7.dist-info/METADATA
c8ydm-1.3.7.dist-info/WHEEL
c8ydm-1.3.7.dist-info/entry_points.txt
c8ydm-1.3.7.dist-info/top_level.txt
c8ydm-1.3.7.dist-info/RECORD
