Metadata-Version: 2.1
Name: c8ydm
Version: 1.3.7
Summary: Cumulocity Device Management Agent
Author: Tobias Sommer, Stefan Witschel, Marco Stoffel, Murat Bayram
Author-email: Stefan.Witschel@softwareag.com
License: Apache 2.0
Requires-Python: >=3.7
License-File: LICENSE
Requires-Dist: paho-mqtt >=1.6.1
Requires-Dist: psutil >=5.9.1
Requires-Dist: requests >=2.28.1
Requires-Dist: c8y-device-proxy >=1.1.1
Requires-Dist: certifi >=2022.6.15
Requires-Dist: distro >=1.7.0
Requires-Dist: sense-hat >=2.3.1
